fastapi_utils_sqlalch2/__init__.py
fastapi_utils_sqlalch2/api_model.py
fastapi_utils_sqlalch2/api_settings.py
fastapi_utils_sqlalch2/camelcase.py
fastapi_utils_sqlalch2/cbv.py
fastapi_utils_sqlalch2/enums.py
fastapi_utils_sqlalch2/guid_type.py
fastapi_utils_sqlalch2/inferring_router.py
fastapi_utils_sqlalch2/openapi.py
fastapi_utils_sqlalch2/py.typed
fastapi_utils_sqlalch2/session.py
fastapi_utils_sqlalch2/tasks.py
fastapi_utils_sqlalch2/timing.py
fastapi_utils_sqlalch2-0.3.0.dist-info/LICENSE
fastapi_utils_sqlalch2-0.3.0.dist-info/METADATA
fastapi_utils_sqlalch2-0.3.0.dist-info/WHEEL
fastapi_utils_sqlalch2-0.3.0.dist-info/RECORD
